seaplane_framework/cli/__init__.py
seaplane_framework/cli/__main__.py
seaplane_framework/cli/auth.py
seaplane_framework/cli/command.py
seaplane_framework/cli/endpoints.py
seaplane_framework/cli/flows.py
seaplane_framework/cli/kv.py
seaplane_framework/cli/objects.py
seaplane_framework/cli/streams.py
seaplane_framework/cli/util.py
seaplane_framework.cli-0.0.19.dist-info/LICENSE
seaplane_framework.cli-0.0.19.dist-info/METADATA
seaplane_framework.cli-0.0.19.dist-info/WHEEL
seaplane_framework.cli-0.0.19.dist-info/entry_points.txt
seaplane_framework.cli-0.0.19.dist-info/top_level.txt
seaplane_framework.cli-0.0.19.dist-info/RECORD
