Metadata-Version: 2.1
Name: seaplane-framework.cli
Version: 0.0.19
Home-page: 
Author: Seaplane IO, Inc.
Author-email: support@seaplane.io
License: Apache 2.0
Keywords: Seaplane,CLI
Requires-Python: >=3.7
License-File: LICENSE
Requires-Dist: PyJWT ==2.8.0
Requires-Dist: PyYAML ==6.0.1
Requires-Dist: click ==8.1.3
Requires-Dist: requests ==2.31.0
Requires-Dist: seaplane-framework.api ~=0.0.13
Requires-Dist: seaplane-framework.common ==0.0.1
Requires-Dist: seaplane-framework.config ==0.0.5
Requires-Dist: sseclient ==0.0.27
Requires-Dist: tabulate
